setup.py
BebrPandasEtl.egg-info/PKG-INFO
BebrPandasEtl.egg-info/SOURCES.txt
BebrPandasEtl.egg-info/dependency_links.txt
BebrPandasEtl.egg-info/requires.txt
BebrPandasEtl.egg-info/top_level.txt
Core/__init__.py