Metadata-Version: 2.1
Name: BebrPandasEtl
Version: 0.1
Home-page: 
Author: Benoit Braeckeveldt
License: MIT
Requires-Dist: pandas
Requires-Dist: lxml
Requires-Dist: diagrams
Requires-Dist: cx
Requires-Dist: tqdm
Requires-Dist: SQLAlchemy
Requires-Dist: openpyxl
Requires-Dist: click
Requires-Dist: mypy-extensions
Requires-Dist: colorama
Requires-Dist: termtables
Requires-Dist: art
Requires-Dist: SQLAlchemy-Utils
Requires-Dist: PySide6
Requires-Dist: fsspec
Requires-Dist: qt-material
